{"topics":[{"id":"541f987963687264fac50100","topic_id":"5161dd617f123bd25900013d","body":"\"@uc9\":/dis/the-time-wasting-thread/post/541f97e163687241375b0000#post_541f97e163687241375b0000\r\nThat's good[spoiler](?)[/spoiler]\r\n\r\n\r\n\"@gasmaskangel\":/dis/the-time-wasting-thread/post/541f97ed6368721e3f720100#post_541f97ed6368721e3f720100\r\nI just don't like them in general. Why would you ruin perfectly good chicken but slathering it in disgusting hot sauce?","author":"4fde4618945b700aa0002fff"},{"id":"541f98bf63687252e0670000","topic_id":"5161dd617f123bd25900013d","body":"\"@SquiggyBomb\":/dis/the-time-wasting-thread/post/541f96ec6368727b38180100#post_541f96ec6368727b38180100\r\noh when we go at it, we're trying everything\r\ntop, bottom, everything in between","author":"4fe3df367f123b517900066a"},{"id":"541f990e6368724dba8d0000","topic_id":"5161dd617f123bd25900013d","body":"\"@mariomarc\":/dis/the-time-wasting-thread/post/541f98bf63687252e0670000#post_541f98bf63687252e0670000\r\nI love the way you think.","author":"4fde4618945b700aa0002fff"},{"id":"541f99176368725663160100","topic_id":"5161dd617f123bd25900013d","body":"\"@SquiggyBomb\":/dis/the-time-wasting-thread/post/541f987963687264fac50100#post_541f987963687264fac50100\r\nBecause chicken is a very mild meat. The sauce is really the most important part, it needs to compliment and add to the chicken instead of over powering it. Most restaurants go the latter route unfortunately.\r\n\r\nI'm just lucky my housemate is a damn good cook.","author":"4f41ee04945b701c41002af7"},{"id":"541f9924636872027ef50100","topic_id":"5161dd617f123bd25900013d","body":"\"@SquiggyBomb\":/dis/the-time-wasting-thread/post/541f987963687264fac50100#post_541f987963687264fac50100\r\n[bq=\"SquiggyBomb\"]I just don't like them in general. Why would you ruin perfectly good chicken but slathering it in disgusting hot sauce?[/bq]\r\n-HOLD THY TONGUE BLASPHEMER LEST YOU POISON INNOCENT MINDS WITH YOUR SINFUL THOUGHTS-\r\n\r\nI disagree","author":"500b587e7f123b1f230014a9"},{"id":"541f992b63687252fe590000","topic_id":"5161dd617f123bd25900013d","body":"hot wings are so impossible to stand for me.\r\n\r\ni just dont stand spicy food in general.\r\n\r\nthere is not a btter way to just make food COMPLETELY UNEATABLE (might as well vomit on it) than putting something spicy in it.","author":"5154c5237f123bcd580002fc"},{"id":"541f99796368724d06900000","topic_id":"5161dd617f123bd25900013d","body":"\"@uc9\":/dis/the-time-wasting-thread/post/541f97e163687241375b0000#post_541f97e163687241375b0000\r\nGlad to hear.","author":"4fde5cee945b700a970060fc"},{"id":"541f99ac6368727b69920100","topic_id":"5161dd617f123bd25900013d","body":"\"@twistedmetalero\":/dis/the-time-wasting-thread/post/541f992b63687252fe590000#post_541f992b63687252fe590000\r\n\r\nWe eat that sh*t for breakfast\r\n\r\n!http://www.thepauperedchef.com/images/2009/08/chilerelleno-17.jpg!","author":"4fdfbf92945b7075d50036e4"},{"id":"541f99bf6368722d43e40000","topic_id":"5161dd617f123bd25900013d","body":"\"@SquiggyBomb\":/dis/the-time-wasting-thread/post/541f987963687264fac50100#post_541f987963687264fac50100\r\nSort of: grandma can now function and can be out of the -asylum- \"home\", but she still needs people to take care of her.  My uncle has had enough cause he's been dealing with this shit for ages, but my mom has for a while wanted grandma to live with her.\r\n\r\nTl:dr; my family is finally stopping being broken.","author":"38b55cdf63616403d7560600"},{"id":"541f99c36368724192630100","topic_id":"5161dd617f123bd25900013d","body":"\"@QuasarNova\":/dis/the-time-wasting-thread/post/541f99ac6368727b69920100#post_541f99ac6368727b69920100\r\n\r\nyour people disgust me.","author":"5154c5237f123bcd580002fc"},{"id":"541f9a0f6368722d66de0000","topic_id":"5161dd617f123bd25900013d","body":"\"@uc9\":/dis/the-time-wasting-thread/post/541f99bf6368722d43e40000#post_541f99bf6368722d43e40000\r\nCongrats. Family is important.","author":"4fde4618945b700aa0002fff"},{"id":"541f9a456368724be0b30000","topic_id":"5161dd617f123bd25900013d","body":"\"@twistedmetalero\":/dis/the-time-wasting-thread/post/541f99c36368724192630100#post_541f99c36368724192630100\r\nWimp","author":"5239db6da4c72d22d9000358"},{"id":"541f9a626368725690700100","topic_id":"5161dd617f123bd25900013d","body":"\"@SquiggyBomb\":/dis/the-time-wasting-thread/post/541f9a0f6368722d66de0000#post_541f9a0f6368722d66de0000\r\n[bq=\"SquiggyBomb\"]\"@uc9\":/dis/the-time-wasting-thread/post/541f99bf6368722d43e40000#post_541f99bf6368722d43e40000\r\nCongrats. Family is important.[/bq]\r\n!http://media-cache-ec0.pinimg.com/236x/3d/dd/99/3ddd9912ba67e81bcb224ec63f65536b.jpg!","author":"38b55cdf63616403d7560600"},{"id":"541f9a856368726e9a650000","topic_id":"5161dd617f123bd25900013d","body":"\"@QuasarNova\":/dis/the-time-wasting-thread/post/541f99ac6368727b69920100#post_541f99ac6368727b69920100\r\nWhat is that\r\nWhy do I want it\r\nWhy do I think it might kill me","author":"500b587e7f123b1f230014a9"},{"id":"541f9a88636872447b030000","topic_id":"5161dd617f123bd25900013d","body":"\"@Shadow_the_Hedgehog\":/dis/the-time-wasting-thread/post/541f9a456368724be0b30000#post_541f9a456368724be0b30000\r\n\r\nbastard.","author":"5154c5237f123bcd580002fc"},{"id":"541f9a9b63687277db580000","topic_id":"5161dd617f123bd25900013d","body":"\"@Shadow_the_Hedgehog\":/dis/the-time-wasting-thread/post/541f9a456368724be0b30000#post_541f9a456368724be0b30000\r\n\r\n\"@twistedmetalero\":/dis/the-time-wasting-thread/post/541f99c36368724192630100#post_541f99c36368724192630100\r\n\r\nFunny thing is the ones used for the pic, aren't even that spicy. You want something that cuts your sense of tase forever?\r\n\r\nManzano or Habanero.","author":"4fdfbf92945b7075d50036e4"},{"id":"541f9ae26368721dd09b0100","topic_id":"5161dd617f123bd25900013d","body":"\"@uc9\":/dis/the-time-wasting-thread/post/541f9a626368725690700100#post_541f9a626368725690700100\r\nLilo and Stitch was such a good movie......","author":"4fde4618945b700aa0002fff"},{"id":"541f9af4636872538b930000","topic_id":"5161dd617f123bd25900013d","body":"omg samurai cop is too much\r\nit's even better with the best friends","author":"4fe3df367f123b517900066a"},{"id":"541f9c186368722d232d0100","topic_id":"5161dd617f123bd25900013d","body":"Oh god you guys\r\nI just logged into Netflix and...\r\n!http://i869.photobucket.com/albums/ab259/potatosoup/imagejpg1_zpse3bd7404.jpg!\r\n...i might have to see if it's as bad as pat and Liam say it is...","author":"500b587e7f123b1f230014a9"},{"id":"541f9d716368726e9af10000","topic_id":"5161dd617f123bd25900013d","body":"\"@Too_Offensive\":/dis/the-time-wasting-thread/post/541f9c186368722d232d0100#post_541f9c186368722d232d0100\r\n\r\nThe first half is decent, until Episode 16-17\r\n\r\nThe seconds half... No comment","author":"4fdfbf92945b7075d50036e4"},{"id":"541f9d756368726de6d30100","topic_id":"5161dd617f123bd25900013d","body":"Awwwww man....\r\n\r\nI was getting hype on Bayo 2 and Max put it on sub only mode. :/\r\n\r\nI cant chat in the comments now. ","author":"50c204917f123b31440000a5"},{"id":"541f9dbd636872538b060100","topic_id":"5161dd617f123bd25900013d","body":"So I found out about Big Hero 6;\r\nI'm modestly hyped.\r\n!http://i0.kym-cdn.com/photos/images/original/000/834/098/87b.gif!","author":"38b55cdf63616403d7560600"},{"id":"541f9dda63687252e0990100","topic_id":"5161dd617f123bd25900013d","body":"One of my favorite Best Friends things; the Anarchy Reigns Brawl! Especially with Pat curb-stomping Matt and Woolie when they thought they were gonna win so easily since Pat lost the prior Brawls.","author":"5056c9e87f123b37f6012a34"},{"id":"541f9ee46368721026400000","topic_id":"5161dd617f123bd25900013d","body":"but BITCH YOU ACTING LIKE YOUR SHIT DONT STANK\r\n(shits real)\r\nBITCH YOU ACTING LIKE YOUR SHIT DONT STANK\r\n(shitville)\r\nBITCH YOU ACTING LIKE YOUR SHIT DONT STANK\r\n(shits real)\r\nBITCH YOU ACTING LIKE YOUR SHIT DONT STANK\r\n(welcome to shitville)","author":"5154c5237f123bcd580002fc"},{"id":"541fa133636872338f320100","topic_id":"5161dd617f123bd25900013d","body":"\"@Too_Offensive\":/dis/the-time-wasting-thread/post/541f9c186368722d232d0100#post_541f9c186368722d232d0100\r\nIt's not as bad as they say it is.\r\n[spoiler]It's waaaaaaaaaaaaaay worse.[/spoiler]\r\n\r\n\"@uc9\":/dis/the-time-wasting-thread/post/541f9dbd636872538b060100#post_541f9dbd636872538b060100\r\nDid you know that Woolie is in that movie?\r\n!www.fatmovieguy.com/wp-content/uploads/2014/07/big-hero-6-cast-wasabi.jpg!\r\n","author":"4fde4618945b700aa0002fff"}]}