{"topics":[{"id":"558f273263687248b2000342","topic_id":"5161dd617f123bd25900013d","body":"\"@Kaz\":/dis/the-time-wasting-thread/post/558f253e63687248bd0000f1#post_558f253e63687248bd0000f1\r\n[bq=\"Kaz\"].\r\n[/bq]\r\n\"­\":http://shut_your_ass,_kaz","author":"50a843d47f123b2e7c001359"},{"id":"558f29b9636872646a001907","topic_id":"5161dd617f123bd25900013d","body":"Master Mao: Jarred cannot be saved because he's too evil.\r\n\r\nCasey: With all due respect Master Mao, go fuck yourself.\r\n\r\nAnd THAT'S why Jungle Fury is awesome.","author":"4fde4618945b700aa0002fff"},{"id":"558f29c2636872646a001914","topic_id":"5161dd617f123bd25900013d","body":"@HELP@\r\n@CAN SOMEONE CAN EXPLAIN THIS?@\r\n\r\n!https://41.media.tumblr.com/8150680384c56873ccbc496da01ddf85/tumblr_nqjwpy2vlM1tyc95yo4_540.png!","author":"31bee2686368722a0df23600"},{"id":"558f2a45636872703900005d","topic_id":"5161dd617f123bd25900013d","body":"\"@Gizoid101\":/dis/the-time-wasting-thread/post/558f29c2636872646a001914#post_558f29c2636872646a001914\r\nyes, fucking hilarity is what it is\r\n\r\nalso i'm requesting canon pony art, take that ocs","author":"50a843d47f123b2e7c001359"},{"id":"558f2b39636872646a001b3d","topic_id":"5161dd617f123bd25900013d","body":"Why rpg's gotta be so long \r\nI wanna play all the rpg's but they so dang ass long ","author":"500b587e7f123b1f230014a9"},{"id":"558f2b4563687248bd00084f","topic_id":"5161dd617f123bd25900013d","body":"\"@Gizoid101\":/dis/the-time-wasting-thread/post/558f29c2636872646a001914#post_558f29c2636872646a001914\r\nNope.","author":"505696b47f123b37e800effa"},{"id":"558f2b5763687248b2000905","topic_id":"5161dd617f123bd25900013d","body":"\"@Gizoid101\":/dis/the-time-wasting-thread/post/558f29c2636872646a001914#post_558f29c2636872646a001914\r\nSomething that Joel from Vinesauce played.\r\n\r\nI'm helping.","author":"5179b098a4c72d9b7f0028ee"},{"id":"558f2c9d6368726fc0001826","topic_id":"5161dd617f123bd25900013d","body":"It's been unusually cool today.","author":"4fde4618945b700aa0002fff"},{"id":"558f2cf96368724f4b0021d7","topic_id":"5161dd617f123bd25900013d","body":"\"@SquiggyBomb\":/dis/the-time-wasting-thread/post/558f2c9d6368726fc0001826#post_558f2c9d6368726fc0001826\r\nHigh amounts of radicality and swood in the atmosphere today","author":"500b587e7f123b1f230014a9"},{"id":"558f2d0863687248b2000b6e","topic_id":"5161dd617f123bd25900013d","body":"\"@SquiggyBomb\":/dis/the-time-wasting-thread/post/558f2c9d6368726fc0001826#post_558f2c9d6368726fc0001826\r\n!https://40.media.tumblr.com/6aa27892a1b0bb02da15748e75cd95ed/tumblr_nqjwpy2vlM1tyc95yo1_540.png!","author":"31bee2686368722a0df23600"},{"id":"558f2d316368726fc00018f5","topic_id":"5161dd617f123bd25900013d","body":"\"@SquiggyBomb\":/dis/the-time-wasting-thread/post/558f2c9d6368726fc0001826#post_558f2c9d6368726fc0001826\r\nIts been hotter than Satans ballsack over here. ","author":"50c204917f123b31440000a5"},{"id":"558f2daa63687248bd000b72","topic_id":"5161dd617f123bd25900013d","body":"I'm just going to assume that none of you guys would be interested in doing a Yo-kai watch stream in a bit.","author":"5062d6f17f123b3e16001184"},{"id":"558f2df26368726fc0001a09","topic_id":"5161dd617f123bd25900013d","body":"\"@SquiggyBomb\":/dis/the-time-wasting-thread/post/558f2c9d6368726fc0001826#post_558f2c9d6368726fc0001826\r\nIt's been hot here for a while now","author":"4fe3df367f123b517900066a"},{"id":"558f2df76368721d900007fb","topic_id":"5161dd617f123bd25900013d","body":"\"@Gizoid101\":/dis/the-time-wasting-thread/post/558f2d0863687248b2000b6e#post_558f2d0863687248b2000b6e\r\nonce again, that's not scary out of context","author":"50a843d47f123b2e7c001359"},{"id":"558f2dfc6368726fc0001a14","topic_id":"5161dd617f123bd25900013d","body":"\"@trashboat\":/dis/the-time-wasting-thread/post/558f2daa63687248bd000b72#post_558f2daa63687248bd000b72\r\nI'm almost finished with Jungle Fury and after that it's back to KH2.","author":"4fde4618945b700aa0002fff"},{"id":"558f2ebc6368724f4b0024c9","topic_id":"5161dd617f123bd25900013d","body":"I'm attempting to get back to a normal sleep schedule, So I'm thinking that streaming could help me stay up in the meantime. (Still have bad luck with streams tho.)","author":"5062d6f17f123b3e16001184"},{"id":"558f2ed463687248b2000e15","topic_id":"5161dd617f123bd25900013d","body":"So, I went to see the movie Spy.\r\nI think I saw dicks.","author":"5446fcfc6368723ec21a0000"},{"id":"558f2f426368727ec700005a","topic_id":"5161dd617f123bd25900013d","body":"!http://simg4.gelbooru.com//images/f0/1e/f01ee2603dc47ea8ece889ddeaf0250a.jpg!\r\n[spoiler]!http://gelbooru.com//images/1c/b2/1cb26cd25a7dfc971745cd014fbce105.jpg![/spoiler]","author":"4fde4618945b700aa0002fff"},{"id":"558f2ff46368726fc0001cfc","topic_id":"5161dd617f123bd25900013d","body":"!http://40.media.tumblr.com/tumblr_lc5rlrmE9V1qb6fkqo1_500.jpg!","author":"4fe3df367f123b517900066a"},{"id":"558f30376368721d90000b18","topic_id":"5161dd617f123bd25900013d","body":"\"@SquiggyBomb\":/dis/the-time-wasting-thread/post/558f2f426368727ec700005a#post_558f2f426368727ec700005a\r\nG'damit! You suck...\r\n:P\r\n\r\n[spoiler]JKING[/spoiler]","author":"4fde5cee945b700a970060fc"},{"id":"558f303a6368727e4400013a","topic_id":"5161dd617f123bd25900013d","body":"\"@trashboat\":/dis/the-time-wasting-thread/post/558f2ebc6368724f4b0024c9#post_558f2ebc6368724f4b0024c9\r\nI'm about to watch Joel play Jojo!","author":"50c204917f123b31440000a5"},{"id":"558f308563687248b2001074","topic_id":"5161dd617f123bd25900013d","body":"NO REALLY.\r\nI THINK I SAW DICKS IN THAT MOVIE.","author":"5446fcfc6368723ec21a0000"},{"id":"558f30f76368724f4b0028af","topic_id":"5161dd617f123bd25900013d","body":"\"@trashboat\":/dis/the-time-wasting-thread/post/558f2ebc6368724f4b0024c9#post_558f2ebc6368724f4b0024c9\r\nI might be up for it in a bit \r\nStill can only do text chat though. ","author":"500b587e7f123b1f230014a9"},{"id":"558f30fc6368726fc0001e9e","topic_id":"5161dd617f123bd25900013d","body":"\"@Carcass Strife\":/dis/the-time-wasting-thread/post/558f308563687248b2001074#post_558f308563687248b2001074\r\nOkay, and?","author":"4fe3df367f123b517900066a"},{"id":"558f312b636872646a0024d5","topic_id":"5161dd617f123bd25900013d","body":"\"@mariomarc\":/dis/the-time-wasting-thread/post/558f30fc6368726fc0001e9e#post_558f30fc6368726fc0001e9e\r\n....mmkay.\r\nAlso, my sister went a little crazy.","author":"5446fcfc6368723ec21a0000"}]}