{"topics":[{"id":"55b14de5636872198e00088d","topic_id":"5161dd617f123bd25900013d","body":"\"@SquiggyBomb\":/dis/the-time-wasting-thread/post/55b14daf636872537700067a#post_55b14daf636872537700067a\r\n*OH!*\r\n\r\n~Weeeeeaaab~","author":"50c204917f123b31440000a5"},{"id":"55b14dfc63687211570009a1","topic_id":"5161dd617f123bd25900013d","body":"\"@Number1pegasus\":/dis/the-time-wasting-thread/post/55b14dca636872115700095a#post_55b14dca636872115700095a\r\n[bq=\"Number1pegasus\"]\"@And Brother I Hurt People\":/dis/the-time-wasting-thread/post/55b14d956368720493000376#post_55b14d956368720493000376\r\nNo problamo!\r\n\r\nAlso, Like I was thinking about doing some kind of funny thing.\r\n\r\nI would draw Applejack cosplaying as characters people requested. [/bq]\r\nTo avoid the cut off. ","author":"50c204917f123b31440000a5"},{"id":"55b14e046368721d9800001e","topic_id":"5161dd617f123bd25900013d","body":"Kissasian has Kamen rider 555 now apparently. (Shame that only Nihon has it. But whatevs)","author":"5062d6f17f123b3e16001184"},{"id":"55b14e08636872198e0008c9","topic_id":"5161dd617f123bd25900013d","body":"\"@Number1pegasus\":/dis/the-time-wasting-thread/post/55b14dca636872115700095a#post_55b14dca636872115700095a\r\n\r\nThat might be fun!","author":"5041b54f7f123b77af00a442"},{"id":"55b14e706368721c280000a7","topic_id":"5161dd617f123bd25900013d","body":"\"@And Brother I Hurt People\":/dis/the-time-wasting-thread/post/55b14e08636872198e0008c9#post_55b14e08636872198e0008c9\r\nDo a you have a request! \r\n\r\nI am all ears! ","author":"50c204917f123b31440000a5"},{"id":"55b14e786368722e9100000b","topic_id":"5161dd617f123bd25900013d","body":"\"To those that are excited for FNAF 4\":https://youtu.be/lVbeFpkJzbI","author":"5446fcfc6368723ec21a0000"},{"id":"55b14ee76368721d98000108","topic_id":"5161dd617f123bd25900013d","body":"\"@Number1pegasus\":/dis/the-time-wasting-thread/post/55b14e706368721c280000a7#post_55b14e706368721c280000a7\r\n\r\nAs to what you should dress Applejack up as? An apple pie?","author":"5041b54f7f123b77af00a442"},{"id":"55b14eed6368721157000b06","topic_id":"5161dd617f123bd25900013d","body":"\"@Carcass Strife\":/dis/the-time-wasting-thread/post/55b14e786368722e9100000b#post_55b14e786368722e9100000b\r\nI'm tempted but I want to see it with Markapilier! ","author":"50c204917f123b31440000a5"},{"id":"55b14ef76368722a250000bd","topic_id":"5161dd617f123bd25900013d","body":"Apparently in the Yo-kai watch games, If you station two Yo-kai of the same type next to each other, Your team gets a stat boost. (Two charmings give a speed boost.)","author":"5062d6f17f123b3e16001184"},{"id":"55b14f026368721c28000163","topic_id":"5161dd617f123bd25900013d","body":"\"@trashboat\":/dis/the-time-wasting-thread/post/55b14e046368721d9800001e#post_55b14e046368721d9800001e\r\nFrom what I read the guys at Kiss REALLY don't want to use the TV-N subs but in some cases they don't have a choice.","author":"4fde4618945b700aa0002fff"},{"id":"55b14f0d636872049300059c","topic_id":"5161dd617f123bd25900013d","body":"\"@Number1pegasus\":/dis/the-time-wasting-thread/post/55b14eed6368721157000b06#post_55b14eed6368721157000b06\r\nHe might not have gotten the demo...","author":"5446fcfc6368723ec21a0000"},{"id":"55b14f1c6368727a080006b2","topic_id":"5161dd617f123bd25900013d","body":"\"@And Brother I Hurt People\":/dis/the-time-wasting-thread/post/55b14ee76368721d98000108#post_55b14ee76368721d98000108\r\n~AND IT BEGINS~","author":"50c204917f123b31440000a5"},{"id":"55b14f2b6368721157000b5a","topic_id":"5161dd617f123bd25900013d","body":"\"@Number1pegasus\":/dis/the-time-wasting-thread/post/55b14f1c6368727a080006b2#post_55b14f1c6368727a080006b2\r\n\r\nYay! It begins!","author":"5041b54f7f123b77af00a442"},{"id":"55b14f476368727a080006ec","topic_id":"5161dd617f123bd25900013d","body":"Leaving early now\r\nParents will be gone till sunday\r\nDrive into work myself tomorrow \r\nLeave early again tomorrow \r\nNice weekend ","author":"4fe3df367f123b517900066a"},{"id":"55b14f806368727a08000730","topic_id":"5161dd617f123bd25900013d","body":"\"@mariomarc\":/dis/the-time-wasting-thread/post/55b14f476368727a080006ec#post_55b14f476368727a080006ec\r\nWhere are mom and dad headed?","author":"4fde4618945b700aa0002fff"},{"id":"55b14f836368721c28000214","topic_id":"5161dd617f123bd25900013d","body":"Sitting in a car.\r\nWith a dog on my lap.\r\nProbably gotta be like this for a while.\r\nHope the dog doesn't throw up.","author":"5446fcfc6368723ec21a0000"},{"id":"55b14f886368724c2500006d","topic_id":"5161dd617f123bd25900013d","body":"\"@SquiggyBomb\":/dis/the-time-wasting-thread/post/55b14f026368721c28000163#post_55b14f026368721c28000163\r\nThat's good at least. (I wonder if there's a way we can get Over-time's W and Go-busters subs on there instead?)","author":"5062d6f17f123b3e16001184"},{"id":"55b1500a6368724c25000109","topic_id":"5161dd617f123bd25900013d","body":"\"@SquiggyBomb\":/dis/the-time-wasting-thread/post/55b14f806368727a08000730#post_55b14f806368727a08000730\r\nOsoyoos \r\nSummer resort lake town\r\nIn only desert in Canada\r\nWe have a small apartment there\r\nHad it for a few years\r\nTrying to sell it\r\nCurrent guy looking has to decide tomorrow night ","author":"4fe3df367f123b517900066a"},{"id":"55b150116368722a25000217","topic_id":"5161dd617f123bd25900013d","body":"\"@trashboat\":/dis/the-time-wasting-thread/post/55b14f886368724c2500006d#post_55b14f886368724c2500006d\r\nWell they are using Orangelion's version of Den-O and I'd assume that when Ghost starts airing they're gonna post the OL subs for it too. So if they had a way to get Over-time's subs they probably would replace the setup they have now.","author":"4fde4618945b700aa0002fff"},{"id":"55b150d16368722e910002cd","topic_id":"5161dd617f123bd25900013d","body":"\"@SquiggyBomb\":/dis/the-time-wasting-thread/post/55b150116368722a25000217#post_55b150116368722a25000217\r\nThere is a request drama and a report error button, But you need facebook.","author":"5062d6f17f123b3e16001184"},{"id":"55b150f86368725377000b3c","topic_id":"5161dd617f123bd25900013d","body":"\"@trashboat\":/dis/the-time-wasting-thread/post/55b150d16368722e910002cd#post_55b150d16368722e910002cd\r\nDAMN YOU FACEBOOOOOOOOK!","author":"4fde4618945b700aa0002fff"},{"id":"55b1513b6368722a250003a3","topic_id":"5161dd617f123bd25900013d","body":"\"@trashboat\":/dis/the-time-wasting-thread/post/55b150d16368722e910002cd#post_55b150d16368722e910002cd\r\n\r\n\"@SquiggyBomb\":/dis/the-time-wasting-thread/post/55b150f86368725377000b3c#post_55b150f86368725377000b3c\r\nWhat's wrong with Facebook? Not that I use it anymore.","author":"5446fcfc6368723ec21a0000"},{"id":"55b151676368727a080009de","topic_id":"5161dd617f123bd25900013d","body":"\"@SquiggyBomb\":/dis/the-time-wasting-thread/post/55b150f86368725377000b3c#post_55b150f86368725377000b3c\r\nYeah. I don't plan on ever getting a facebook.\r\n\r\nAnyway, If you provided them a functional link to the Over-time subs. They would probably accept it.","author":"5062d6f17f123b3e16001184"},{"id":"55b152946368727a08000b89","topic_id":"5161dd617f123bd25900013d","body":"\"@And Brother I Hurt People\":/dis/the-time-wasting-thread/post/55b14f2b6368721157000b5a#post_55b14f2b6368721157000b5a\r\nI have done it!\r\n\r\nAnyone else got any request for Applejack to cosplay as? ","author":"50c204917f123b31440000a5"},{"id":"55b152d86368724c2500042d","topic_id":"5161dd617f123bd25900013d","body":"\"@Number1pegasus\":/dis/the-time-wasting-thread/post/55b152946368727a08000b89#post_55b152946368727a08000b89\r\nYou drawing?\r\n\r\nHow about Bunnie Rabbot?","author":"4fe3df367f123b517900066a"}]}