{"topics":[{"id":"548c5ba86368722c2dce0700","topic_id":"5161dd617f123bd25900013d","body":"\"@ParagonCommander\":/dis/the-time-wasting-thread/post/548c5aa36368727d567d0300#post_548c5aa36368727d567d0300\r\n\r\nThat's not how you spell trashboat.\r\n\r\n\r\n\"@Zak_Inc\":/dis/the-time-wasting-thread/post/548c5a9c6368721244810400#post_548c5a9c6368721244810400\r\n\r\nI'd say you're getting rancid.\r\n\r\n\r\n\r\n\"@Miyo\":/dis/the-time-wasting-thread/post/548c5adb6368720dd3d10100#post_548c5adb6368720dd3d10100\r\n\r\nWhen was I even fresh meat? Hasn't Derpibooru just been a daily part of my routine? Oh God, how did I get here? Is there an end to the suffering?\r\n\r\n\r\n\"@Patologička\":/dis/the-time-wasting-thread/post/548c5ae06368723396e10100#post_548c5ae06368723396e10100\r\n\r\nNah, talk. It's more fun that way.","author":"5041b54f7f123b77af00a442"},{"id":"548c5bd36368722874ac0400","topic_id":"5161dd617f123bd25900013d","body":"\"@Miyo\":/dis/the-time-wasting-thread/post/548c5adb6368720dd3d10100#post_548c5adb6368720dd3d10100\r\nYou're new?\r\nAnd yet you have 6455 posts.\r\n\r\nI've been here for OVER A YEAR and I don't have that many posts.\r\n\r\n\r\n\"@Patologička\":/dis/the-time-wasting-thread/post/548c5ae06368723396e10100#post_548c5ae06368723396e10100\r\nJust so you know, there are a few 'unofficial rules' of the forums that I totally didn't make up.\r\n\r\n1. Every conversation can - and will - come back to Revengeance.\r\n2. If Rule 1 is defied, then it will come back to Yuugi from Touhou instead.\r\n3. Trashboat will post whatever the hell he wants.\r\n4. Number1Pegasus fights for his friends\r\n5. I tip the scales around here.\r\n6. If you go near the Fetishes thread, be ready to see some _weird shit_.","author":"515ddf93a4c72d8a1f000d57"},{"id":"548c5c296368720daff70100","topic_id":"5161dd617f123bd25900013d","body":"\"@ParagonCommander\":/dis/the-time-wasting-thread/post/548c5bd36368722874ac0400#post_548c5bd36368722874ac0400\r\n\r\nTake number three to heart. Smile and nod when he talks about his Caramel Riders or something.\r\n\r\n-~we love you based trashboat~-","author":"5041b54f7f123b77af00a442"},{"id":"548c5c3d6368720cb72d0200","topic_id":"5161dd617f123bd25900013d","body":"\"@ParagonCommander\":/dis/the-time-wasting-thread/post/548c5bd36368722874ac0400#post_548c5bd36368722874ac0400\r\n\r\nI changed my name to Miyo.\r\n\r\n-i think ive been here for.. 3 years? the second year i abandoned the site-","author":"511c09ec7f123b35980001eb"},{"id":"548c5c746368720e29cc0100","topic_id":"5161dd617f123bd25900013d","body":"\"@And Brother I Hurt People\":/dis/the-time-wasting-thread/post/548c5c296368720daff70100#post_548c5c296368720daff70100\r\n\"\"Caramel Riders\"\":https://www.youtube.com/watch?v=pPT1hmQV_6Q","author":"515ddf93a4c72d8a1f000d57"},{"id":"548c5c9863687211e04a0400","topic_id":"5161dd617f123bd25900013d","body":"\"@Miyo\":/dis/the-time-wasting-thread/post/548c5c3d6368720cb72d0200#post_548c5c3d6368720cb72d0200\r\nWhat was your original name?","author":"515ddf93a4c72d8a1f000d57"},{"id":"548c5cba6368720f61080200","topic_id":"5161dd617f123bd25900013d","body":"\"@ParagonCommander\":/dis/the-time-wasting-thread/post/548c5c746368720e29cc0100#post_548c5c746368720e29cc0100\r\n\r\nShouldn't another rule be that we always find a way to incorporate Jontren?","author":"5041b54f7f123b77af00a442"},{"id":"548c5d066368721244a80400","topic_id":"5161dd617f123bd25900013d","body":"\"@And Brother I Hurt People\":/dis/the-time-wasting-thread/post/548c5cba6368720f61080200#post_548c5cba6368720f61080200\r\nIs Jontren a form of Jontron, because if yes then i vote we make that a rule.","author":"5307a92d6368722c6c0d0100"},{"id":"548c5d6b6368720cb73e0200","topic_id":"5161dd617f123bd25900013d","body":"\"@Zak_Inc\":/dis/the-time-wasting-thread/post/548c5d066368721244a80400#post_548c5d066368721244a80400\r\n\r\nYes.\r\n\r\n!http://www.tubefilter.com/wp-content/uploads/2014/05/jontron-show-600x368.jpg!","author":"5041b54f7f123b77af00a442"},{"id":"548c5d6c6368720daf0f0200","topic_id":"5161dd617f123bd25900013d","body":"\"@ParagonCommander\":/dis/the-time-wasting-thread/post/548c5c9863687211e04a0400#post_548c5c9863687211e04a0400\r\n\r\nIt was [spoiler][_*REDACTED INFORMATION*_][/spoiler]","author":"511c09ec7f123b35980001eb"},{"id":"548c5da463687265339c0500","topic_id":"5161dd617f123bd25900013d","body":"\"@Zak_Inc\":/dis/the-time-wasting-thread/post/548c5ba26368720980f40400#post_548c5ba26368720980f40400\r\nB-but.. What should I... say","author":"548c55d76368727c37650000"},{"id":"548c5de363687233960f0200","topic_id":"5161dd617f123bd25900013d","body":"\"@Zak_Inc\":/dis/the-time-wasting-thread/post/548c5d066368721244a80400#post_548c5d066368721244a80400\r\n!http://i1.kym-cdn.com/photos/images/newsfeed/000/857/624/203.gif!","author":"515ddf93a4c72d8a1f000d57"},{"id":"548c5de56368720d9a6a0200","topic_id":"5161dd617f123bd25900013d","body":"\"@Patologička\":/dis/the-time-wasting-thread/post/548c5da463687265339c0500#post_548c5da463687265339c0500\r\n\r\nWords, worries, -porn.-","author":"5041b54f7f123b77af00a442"},{"id":"548c5e0b6368720e9d620200","topic_id":"5161dd617f123bd25900013d","body":"Ey, guis\r\n!http://uproxx.files.wordpress.com/2012/10/window-jump.gif!\r\n~damnit, wrong way~","author":"5446fcfc6368723ec21a0000"},{"id":"548c5e656368724c95ef0100","topic_id":"5161dd617f123bd25900013d","body":"\"@And Brother I Hurt People\":/dis/the-time-wasting-thread/post/548c5de56368720d9a6a0200#post_548c5de56368720d9a6a0200\r\nI like talking about porn","author":"548c55d76368727c37650000"},{"id":"548c5e806368727d56c50300","topic_id":"5161dd617f123bd25900013d","body":"\"@And Brother I Hurt People\":/dis/the-time-wasting-thread/post/548c5d6b6368720cb73e0200#post_548c5d6b6368720cb73e0200\r\n\r\n\"@ParagonCommander\":/dis/the-time-wasting-thread/post/548c5de363687233960f0200#post_548c5de363687233960f0200\r\nOH BOY\r\n\r\n!http://i.imgur.com/Wgx7EwL.gif!","author":"5307a92d6368722c6c0d0100"},{"id":"548c5e8a6368720ed51f0200","topic_id":"5161dd617f123bd25900013d","body":"!http://i.imgur.com/AmZ0VfY.gif!","author":"511c09ec7f123b35980001eb"},{"id":"548c5f076368720e161d0200","topic_id":"5161dd617f123bd25900013d","body":"\"@Patologička\":/dis/the-time-wasting-thread/post/548c5e656368724c95ef0100#post_548c5e656368724c95ef0100\r\nThen you might fit in well around here.\r\n\r\nI feel like I should give you information on everyone here, military style or something.","author":"515ddf93a4c72d8a1f000d57"},{"id":"548c5f1b6368722874e60400","topic_id":"5161dd617f123bd25900013d","body":"\"@Patologička\":/dis/the-time-wasting-thread/post/548c5e656368724c95ef0100#post_548c5e656368724c95ef0100\r\n\r\nTalk about porn, then.\r\n\r\n\r\n\"@Zak_Inc\":/dis/the-time-wasting-thread/post/548c5e806368727d56c50300#post_548c5e806368727d56c50300\r\n\r\n\"@Miyo\":/dis/the-time-wasting-thread/post/548c5e8a6368720ed51f0200#post_548c5e8a6368720ed51f0200\r\n\r\n!http://33.media.tumblr.com/cf636ed296ce24c44b542a331273e210/tumblr_n77zliQTHi1qa4rnxo3_r1_500.gif! ","author":"5041b54f7f123b77af00a442"},{"id":"548c5fbc63687212750f0400","topic_id":"5161dd617f123bd25900013d","body":"!http://i.imgur.com/WZetNZD.gif!","author":"511c09ec7f123b35980001eb"},{"id":"548c607a6368720bf7790200","topic_id":"5161dd617f123bd25900013d","body":"\"@ParagonCommander\":/dis/the-time-wasting-thread/post/548c5f076368720e161d0200#post_548c5f076368720e161d0200\r\nQuestion.\r\nDoes your controller take a long time to charge?","author":"5446fcfc6368723ec21a0000"},{"id":"548c607b636872120bb90400","topic_id":"5161dd617f123bd25900013d","body":"!http://i.imgur.com/6X1Ormk.gif!","author":"5307a92d6368722c6c0d0100"},{"id":"548c61436368720e9da10200","topic_id":"5161dd617f123bd25900013d","body":"\"@Carcass Strife\":/dis/the-time-wasting-thread/post/548c607a6368720bf7790200#post_548c607a6368720bf7790200\r\nOh, it's charged.\r\nBut when I sent you my GT, it was 12AM.\r\nI kinda need to sleep, y'know?","author":"515ddf93a4c72d8a1f000d57"},{"id":"548c614c6368722874210500","topic_id":"5161dd617f123bd25900013d","body":"!http://i.minus.com/ivBQlYLxlHiKF.gif!","author":"5041b54f7f123b77af00a442"},{"id":"548c61fd6368727bb0100100","topic_id":"5161dd617f123bd25900013d","body":"!http://stream1.gifsoup.com/view4/20140612/5050969/jontron-blood-puke-o.gif!\r\n\r\n-this is my favorite-","author":"511c09ec7f123b35980001eb"}]}