{"topics":[{"id":"557115296368727fed110000","topic_id":"5161dd617f123bd25900013d","body":"\"@SquiggyBomb\":/dis/the-time-wasting-thread/post/557110146368721ecd6f0b00#post_557110146368721ecd6f0b00\r\n[bq=\"SquiggyBomb\"]So what have you bunch of nerds been doing today?[/bq]\r\nWatching real people dying.\r\n\r\n\"@Too_Offensive\":/dis/the-time-wasting-thread/post/5571125163687250c85e0700#post_5571125163687250c85e0700\r\n\"@Number1pegasus\":/dis/the-time-wasting-thread/post/5571129963687250c8dc0700#post_5571129963687250c8dc0700\r\nI would worry if I were you if I have sleep problems.\r\n\r\n\"@SeraphimDawn\":/dis/the-time-wasting-thread/post/5571140f636872542c200000#post_5571140f636872542c200000\r\nHe's busy.","author":"5239db6da4c72d22d9000358"},{"id":"557115626368727fb5810000","topic_id":"5161dd617f123bd25900013d","body":"\"@trashboat\":/dis/the-time-wasting-thread/post/557113ed63687264a0871500#post_557113ed63687264a0871500\r\nI knew that voice sounded familiar!\r\n\r\n\r\n\"@SeraphimDawn\":/dis/the-time-wasting-thread/post/5571140f636872542c200000#post_5571140f636872542c200000\r\nhe's probably out doing something? \r\n\r\n","author":"50c204917f123b31440000a5"},{"id":"557115766368727fb5ab0000","topic_id":"5161dd617f123bd25900013d","body":"\"@Kaz\":/dis/the-time-wasting-thread/post/557114d46368722c9f8a2500#post_557114d46368722c9f8a2500\r\nBloody adorable! \r\n\r\n","author":"50c204917f123b31440000a5"},{"id":"557115bf6368720186e20000","topic_id":"5161dd617f123bd25900013d","body":"\"@Number1pegasus\":/dis/the-time-wasting-thread/post/557115626368727fb5810000#post_557115626368727fb5810000\r\nIt's kind of weird to hear him in a role like that.","author":"5062d6f17f123b3e16001184"},{"id":"557115c66368720150150100","topic_id":"5161dd617f123bd25900013d","body":"\"@Kaz\":/dis/the-time-wasting-thread/post/557114d46368722c9f8a2500#post_557114d46368722c9f8a2500\r\n[bq=\"Kaz\"]:D  15$ !http://pre03.deviantart.net/bc3e/th/pre/i/2015/155/5/b/request_from_astral_bltzen_by_ellinoir-d8w0920.png![/bq]\r\n\r\nIkr :D and it was free","author":"37e5b9d66361642500af5e00"},{"id":"557115d7636872013b5b0100","topic_id":"5161dd617f123bd25900013d","body":"News:\r\nHillary is calling for all eligible voters to automatically be eligible for voting.\r\n\r\n\r\nBasically rather than registering to vote you would automatically be registered and just need to show up with a usa ID of some sort.  It actually probably will happen in the long run because the democrats would profit greatly cause when she becomes president it would effectively shut out republicans from florida and ohio.\r\n\r\n\r\nTl:dr; in a couple years usa citizens will automatically be registered as voters cause it will benefit democrats voting wise.","author":"38b55cdf63616403d7560600"},{"id":"557116286368720150af0100","topic_id":"5161dd617f123bd25900013d","body":"\"@Kaz\":/dis/the-time-wasting-thread/post/557115c66368720150150100#post_557115c66368720150150100\r\nHurray for fucking free!\r\n\r\n\r\n\"@trashboat\":/dis/the-time-wasting-thread/post/557115bf6368720186e20000#post_557115bf6368720186e20000\r\nIt is, I'm so used to him playing as older people. \r\n\r\nBut he does the job pretty nicely though!","author":"50c204917f123b31440000a5"},{"id":"5571167c6368727fd6770200","topic_id":"5161dd617f123bd25900013d","body":"\"@Kaz\":/dis/the-time-wasting-thread/post/557115c66368720150150100#post_557115c66368720150150100\r\nWhere you find free request?\r\nIn DA or in Tumblr?","author":"5239db6da4c72d22d9000358"},{"id":"557116be6368727f919b0300","topic_id":"5161dd617f123bd25900013d","body":"Well I'm gonna clean my glasses, -masturbate-, and play more Wind Waker.","author":"4fde4618945b700aa0002fff"},{"id":"5571170d6368727fb5e90300","topic_id":"5161dd617f123bd25900013d","body":"\"@Shadow the Hedgehog\":/dis/the-time-wasting-thread/post/5571167c6368727fd6770200#post_5571167c6368727fd6770200\r\n[bq=\"Shadow the Hedgehog\"]\"@Kaz\":/dis/the-time-wasting-thread/post/557115c66368720150150100#post_557115c66368720150150100\r\nWhere you find free request?\r\nIn DA or in Tumblr?[/bq]\r\nDA\"@Number1pegasus\":/dis/the-time-wasting-thread/post/557116286368720150af0100#post_557116286368720150af0100\r\n[bq=\"Number1pegasus\"]\"@Kaz\":/dis/the-time-wasting-thread/post/557115c66368720150150100#post_557115c66368720150150100\r\nHurray for fucking free!\r\n\r\n\r\n\"@trashboat\":/dis/the-time-wasting-thread/post/557115bf6368720186e20000#post_557115bf6368720186e20000\r\nIt is, I'm so used to him playing as older people. \r\n\r\nBut he does the job pretty nicely though![/bq]\r\nYayayyyyyaaaaaa","author":"37e5b9d66361642500af5e00"},{"id":"55711721636872073da70200","topic_id":"5161dd617f123bd25900013d","body":"\"@Number1pegasus\":/dis/the-time-wasting-thread/post/557116286368720150af0100#post_557116286368720150af0100\r\nAlso, I managed to convince squiggy to watch it just because he's in it.","author":"5062d6f17f123b3e16001184"},{"id":"557117716368727f91fa0400","topic_id":"5161dd617f123bd25900013d","body":"\"@trashboat\":/dis/the-time-wasting-thread/post/55711721636872073da70200#post_55711721636872073da70200\r\nHURRAY! MORE PEOPLE ON THE TRAIN!","author":"50c204917f123b31440000a5"},{"id":"557117f363687201862f0400","topic_id":"5161dd617f123bd25900013d","body":"\"@trashboat\":/dis/the-time-wasting-thread/post/55711721636872073da70200#post_55711721636872073da70200\r\n[bq=\"trashboat\"]\"@Number1pegasus\":/dis/the-time-wasting-thread/post/557116286368720150af0100#post_557116286368720150af0100\r\nAlso, I managed to convince squiggy to watch it just because he's in it.[/bq]\r\nI managed to not care","author":"37e5b9d66361642500af5e00"},{"id":"5571186e6368720186d90400","topic_id":"5161dd617f123bd25900013d","body":"\"@Kaz\":/dis/the-time-wasting-thread/post/557117f363687201862f0400#post_557117f363687201862f0400\r\nStop that. ","author":"50c204917f123b31440000a5"},{"id":"557118746368727fd6ee0500","topic_id":"5161dd617f123bd25900013d","body":"\"@trashboat\":/dis/the-time-wasting-thread/post/55711721636872073da70200#post_55711721636872073da70200\r\ndoraemon seems like one of those things that's prominent enough that I should probably know more about it than just \"blue cat thing\" ","author":"500b587e7f123b1f230014a9"},{"id":"557118a0636872073da40400","topic_id":"5161dd617f123bd25900013d","body":"I had a deep hate towards Doraemon when I was young.","author":"5239db6da4c72d22d9000358"},{"id":"557118a56368727fb5e60600","topic_id":"5161dd617f123bd25900013d","body":"\"@Too_Offensive\":/dis/the-time-wasting-thread/post/557118746368727fd6ee0500#post_557118746368727fd6ee0500\r\nI'd say you'd probably enjoy the series. Its pretty funny!","author":"50c204917f123b31440000a5"},{"id":"5571192b6368720150410600","topic_id":"5161dd617f123bd25900013d","body":"\"@Number1pegasus\":/dis/the-time-wasting-thread/post/557118a56368727fb5e60600#post_557118a56368727fb5e60600\r\nis it one of those wacky slice of life type type things","author":"500b587e7f123b1f230014a9"},{"id":"5571194e6368721f83170000","topic_id":"5161dd617f123bd25900013d","body":"\"@SquiggyBomb\":/dis/the-time-wasting-thread/post/557110e563687264a0d80f00#post_557110e563687264a0d80f00\r\noh then you're pretty close to the real meat of the game\r\n\r\nthough im curius, you think it lives up to it's unanimous praise?","author":"50a843d47f123b2e7c001359"},{"id":"5571195c6368721f8f2c0000","topic_id":"5161dd617f123bd25900013d","body":"That moment when Doraemon is considered to be more powerful than Kenshiro.","author":"5239db6da4c72d22d9000358"},{"id":"55711a2a6368721fcb4f0100","topic_id":"5161dd617f123bd25900013d","body":"Welllll this thread is dead :(","author":"37e5b9d66361642500af5e00"},{"id":"55711a666368721fb8c80100","topic_id":"5161dd617f123bd25900013d","body":"\"@Shadow the Hedgehog\":/dis/the-time-wasting-thread/post/5571195c6368721f8f2c0000#post_5571195c6368721f8f2c0000\r\nHe has a 4th dimensional pocket filled with all sorts of gadgets. There's bound to be one for nearly any situation.","author":"5062d6f17f123b3e16001184"},{"id":"55711ad46368721f83190300","topic_id":"5161dd617f123bd25900013d","body":"\"@Too_Offensive\":/dis/the-time-wasting-thread/post/5571192b6368720150410600#post_5571192b6368720150410600\r\nI guess you can call it that, Its pretty fun too!\r\n\r\n\r\n\"@Shadow the Hedgehog\":/dis/the-time-wasting-thread/post/5571195c6368721f8f2c0000#post_5571195c6368721f8f2c0000\r\n\r\n\"@trashboat\":/dis/the-time-wasting-thread/post/55711a666368721fb8c80100#post_55711a666368721fb8c80100\r\nDoraemon fucking pulls some Kung Fu shit. ","author":"50c204917f123b31440000a5"},{"id":"55711ad96368721f8f020300","topic_id":"5161dd617f123bd25900013d","body":"\"@Kaz\":/dis/the-time-wasting-thread/post/55711a2a6368721fcb4f0100#post_55711a2a6368721fcb4f0100\r\n[bq=\"Kaz\"]Welllll this thread is dead :([/bq]\r\n!http://img0.joyreactor.com/pics/post/funny-pictures-auto-Pokemon-photo-364369.jpeg!","author":"38b55cdf63616403d7560600"},{"id":"55711af76368721f83530300","topic_id":"5161dd617f123bd25900013d","body":"\"@uc9\":/dis/the-time-wasting-thread/post/55711ad96368721f8f020300#post_55711ad96368721f8f020300\r\n~Is that Trashbait?~","author":"50c204917f123b31440000a5"}]}