{"topics":[{"id":"54dc51626368726136a60d00","topic_id":"5161dd617f123bd25900013d","body":"\"@trashboat\":/dis/the-time-wasting-thread/post/54dc50e763687240c2b40000#post_54dc50e763687240c2b40000\r\nThat is just begging for an \"Excuse me?\" at the beginning followed by a \"Say that again\" at the end,","author":"509f70a87f123b77eb0004fd"},{"id":"54dc518163687223ce420100","topic_id":"5161dd617f123bd25900013d","body":"So I just thought of something\r\n\r\nWe've seen Arthur's hamster and uncle so far\r\nWe've seen Lewis' foster parents\r\nAnd we've seen that tree lady who's most likely related to Mystery somehow\r\n*_Nothing from Vivi's background though_*\r\n\r\nJust a thought","author":"9ba2e84e636164642cc03200"},{"id":"54dc519f63687222bad81000","topic_id":"5161dd617f123bd25900013d","body":"So here wants to here a Touhou version of the song Toxic by Britney Spears?\r\n\r\n\"Because that fucking exists.\r\nAnd it's kind of rad.\":https://www.youtube.com/watch?v=oX04fZSjPQ8","author":"4fde4618945b700aa0002fff"},{"id":"54dc52b16368721787e40100","topic_id":"5161dd617f123bd25900013d","body":"\"@SquiggyBomb\":/dis/the-time-wasting-thread/post/54dc519f63687222bad81000#post_54dc519f63687222bad81000\r\nEh not bad,","author":"509f70a87f123b77eb0004fd"},{"id":"54dc52c56368721787f10100","topic_id":"5161dd617f123bd25900013d","body":"\"@Thanotos Omega\":/dis/the-time-wasting-thread/post/54dc51626368726136a60d00#post_54dc51626368726136a60d00\r\nAlso,\r\n\r\n!http://www.entertainmentearth.com/images/AUTOIMAGES/HNT821161lg.jpg!\r\n>Saying that while Great Mazinger exists","author":"5062d6f17f123b3e16001184"},{"id":"54dc534e6368723c0be70200","topic_id":"5161dd617f123bd25900013d","body":"\"@trashboat\":/dis/the-time-wasting-thread/post/54dc52c56368721787f10100#post_54dc52c56368721787f10100\r\nLook when he punch-grabs something with lighting then kicks then we will talk,","author":"509f70a87f123b77eb0004fd"},{"id":"54dc546663687250d8fe0200","topic_id":"5161dd617f123bd25900013d","body":"Well I'm going to bed\r\nNight all","author":"4fe3df367f123b517900066a"},{"id":"54dc554b6368723c05dd1c00","topic_id":"5161dd617f123bd25900013d","body":"!https://36.media.tumblr.com/27ae29d8f63361303ebc3e37fdbb4fec/tumblr_mt4nyjXz951so5kkno1_1280.jpg!","author":"5062d6f17f123b3e16001184"},{"id":"54dc58cf6368727ac6830a00","topic_id":"5161dd617f123bd25900013d","body":"Iyo can shoot a beam from between her ears for some reason.","author":"5062d6f17f123b3e16001184"},{"id":"54dc5e8463687245435f0000","topic_id":"5161dd617f123bd25900013d","body":"as of right now i was told by particle that she will be recurring to physical violence if i talk shit about her back again.\r\n\r\ni told her that she was a nerd and to fight me irl.","author":"5154c5237f123bcd580002fc"},{"id":"54dc60a06368727719f70000","topic_id":"5161dd617f123bd25900013d","body":"\"@Twisty\":/dis/the-time-wasting-thread/post/54dc5e8463687245435f0000#post_54dc5e8463687245435f0000\r\n[bq=\"Twisty\"]as of right now i was told by particle that she will be recurring to physical violence if i talk shit about her back again.\r\n\r\ni told her that she was a nerd and to fight me irl.[/bq]\r\n!http://i.imgur.com/Yri7XXr.png!\r\n\r\n!http://i.imgur.com/hVT4ceU.png!","author":"5415070c636872781bea0000"},{"id":"54dc60f063687221c42d0e00","topic_id":"5161dd617f123bd25900013d","body":"\"@ParticleMare\":/dis/the-time-wasting-thread/post/54dc60a06368727719f70000#post_54dc60a06368727719f70000\r\n[bq=\"ParticleMare\"]\"@Twisty\":/dis/the-time-wasting-thread/post/54dc5e8463687245435f0000#post_54dc5e8463687245435f0000\r\n[bq=\"Twisty\"]as of right now i was told by particle that she will be recurring to physical violence if i talk shit about her back again.\r\n\r\ni told her that she was a nerd and to fight me irl.[/bq]\r\n!http://i.imgur.com/Yri7XXr.png!\r\n\r\n!http://i.imgur.com/hVT4ceU.png![/bq]\r\n\r\nyou are such a bitch you know that ","author":"5154c5237f123bcd580002fc"},{"id":"54dc620663687275afb00900","topic_id":"5161dd617f123bd25900013d","body":"\"@Twisty\":/dis/the-time-wasting-thread/post/54dc60f063687221c42d0e00#post_54dc60f063687221c42d0e00\r\n[bq=\"Twisty\"]\"@ParticleMare\":/dis/the-time-wasting-thread/post/54dc60a06368727719f70000#post_54dc60a06368727719f70000\r\n[bq=\"ParticleMare\"]\"@Twisty\":/dis/the-time-wasting-thread/post/54dc5e8463687245435f0000#post_54dc5e8463687245435f0000\r\n[bq=\"Twisty\"]as of right now i was told by particle that she will be recurring to physical violence if i talk shit about her back again.\r\n\r\ni told her that she was a nerd and to fight me irl.[/bq]\r\n!http://i.imgur.com/Yri7XXr.png!\r\n\r\n!http://i.imgur.com/hVT4ceU.png![/bq]\r\n\r\nyou are such a bitch you know that [/bq]\r\n\r\ngo tell that to ur friends coz guess what, i'm no longer one of them lmao","author":"5415070c636872781bea0000"},{"id":"54dc626d63687255be600700","topic_id":"5161dd617f123bd25900013d","body":"\"@ParticleMare\":/dis/the-time-wasting-thread/post/54dc620663687275afb00900#post_54dc620663687275afb00900\r\n\r\nis that how we are gonna play?\r\n\r\nfine you big bully\r\n\r\n;((((","author":"5154c5237f123bcd580002fc"},{"id":"54dc632a6368726c35750300","topic_id":"5161dd617f123bd25900013d","body":"\"@ParticleMare\":/dis/the-time-wasting-thread/post/54dc620663687275afb00900#post_54dc620663687275afb00900\r\n\r\n\"@Twisty\":/dis/the-time-wasting-thread/post/54dc626d63687255be600700#post_54dc626d63687255be600700\r\nIf you two keep bringing your shit into the glorious master thread I'm going to poke you guys in the eyes with salad forks.","author":"5062d6f17f123b3e16001184"},{"id":"54dc636d6368722b953d0500","topic_id":"5161dd617f123bd25900013d","body":"\"@trashboat\":/dis/the-time-wasting-thread/post/54dc632a6368726c35750300#post_54dc632a6368726c35750300\r\nhe started it by being a fuckboy","author":"5415070c636872781bea0000"},{"id":"54dc63936368725370900500","topic_id":"5161dd617f123bd25900013d","body":"\"@ParticleMare\":/dis/the-time-wasting-thread/post/54dc636d6368722b953d0500#post_54dc636d6368722b953d0500\r\n\r\nyou started it by being a bully\r\n\r\n","author":"5154c5237f123bcd580002fc"},{"id":"54dc63cb63687229bef83e00","topic_id":"5161dd617f123bd25900013d","body":"\"@ParticleMare\":/dis/the-time-wasting-thread/post/54dc636d6368722b953d0500#post_54dc636d6368722b953d0500\r\n!http://images.onesite.com/capcom-unity.com/user/daggerx/a358cc81663731315415283d944a07a0.jpg?v=76800!\r\n*NOW YOU'RE SPEAKING MY LANGUAGE!*","author":"5062d6f17f123b3e16001184"},{"id":"54dc640d63687222a4860500","topic_id":"5161dd617f123bd25900013d","body":"\"@ParticleMare\":/dis/the-time-wasting-thread/post/54dc636d6368722b953d0500#post_54dc636d6368722b953d0500\r\n\"@ParticleMare\":/dis/the-time-wasting-thread/post/54dc636d6368722b953d0500#post_54dc636d6368722b953d0500\r\nOhhhh its so beautiful the love :3","author":"5239db6da4c72d22d9000358"},{"id":"54dc64c26368723c73ea0900","topic_id":"5161dd617f123bd25900013d","body":"\"@Shadow the Hedgehog\":/dis/the-time-wasting-thread/post/54dc640d63687222a4860500#post_54dc640d63687222a4860500\r\n\r\new no, she is a nerd and a bully","author":"5154c5237f123bcd580002fc"},{"id":"54dc651963687243e7543a00","topic_id":"5161dd617f123bd25900013d","body":"\"@Twisty\":/dis/the-time-wasting-thread/post/54dc64c26368723c73ea0900#post_54dc64c26368723c73ea0900\r\nyou know what? I'm just going to stop talking to you. I'm over you, alright? I'm not going to let you annoy me ever again. From now on, you are gone from my life","author":"5415070c636872781bea0000"},{"id":"54dc65456368721b728a1100","topic_id":"5161dd617f123bd25900013d","body":"\"@Twisty\":/dis/the-time-wasting-thread/post/54dc64c26368723c73ea0900#post_54dc64c26368723c73ea0900\r\nYou both are nerds. Loving nerds.\r\nShe do that because she likes you ¬u¬\r\n\r\n\"@ParticleMare\":/dis/the-time-wasting-thread/post/54dc651963687243e7543a00#post_54dc651963687243e7543a00\r\nSee?","author":"5239db6da4c72d22d9000358"},{"id":"54dc656e636872214bc70000","topic_id":"5161dd617f123bd25900013d","body":"\"@ParticleMare\":/dis/the-time-wasting-thread/post/54dc651963687243e7543a00#post_54dc651963687243e7543a00\r\n[spoiler]Could we have you here instead of Twisty?[/spoiler]","author":"5062d6f17f123b3e16001184"},{"id":"54dc65746368726686300300","topic_id":"5161dd617f123bd25900013d","body":"\"@ParticleMare\":/dis/the-time-wasting-thread/post/54dc651963687243e7543a00#post_54dc651963687243e7543a00\r\n\r\nno plz, who will play cry of fear with me ;(((","author":"5154c5237f123bcd580002fc"},{"id":"54dc65e563687231d1a10000","topic_id":"5161dd617f123bd25900013d","body":"\"@Twisty\":/dis/the-time-wasting-thread/post/54dc65746368726686300300#post_54dc65746368726686300300\r\nWith your other friends from here?\r\n:\\","author":"5239db6da4c72d22d9000358"}]}